LICENSE
MANIFEST.in
README.md
RELEASE-VERSION
ez_setup.py
py7zlib.py
setup.cfg
setup.py
version.py
doc/THANKS.md
doc/USAGE.md
pylzma.egg-info/PKG-INFO
pylzma.egg-info/SOURCES.txt
pylzma.egg-info/dependency_links.txt
pylzma.egg-info/not-zip-safe
pylzma.egg-info/requires.txt
pylzma.egg-info/top_level.txt
src/7zip/C/Aes.c
src/7zip/C/Aes.h
src/7zip/C/AesOpt.c
src/7zip/C/Bra.c
src/7zip/C/Bra.h
src/7zip/C/Bra86.c
src/7zip/C/BraIA64.c
src/7zip/C/CpuArch.c
src/7zip/C/CpuArch.h
src/7zip/C/RotateDefs.h
src/7zip/C/Sha256.c
src/7zip/C/Sha256.h
src/compat/LzmaCompatDecode.c
src/compat/LzmaCompatDecode.h
src/compat/copying.txt
src/pylzma/pylzma.c
src/pylzma/pylzma.h
src/pylzma/pylzma_aes.c
src/pylzma/pylzma_aes.h
src/pylzma/pylzma_compress.c
src/pylzma/pylzma_compress.h
src/pylzma/pylzma_compressfile.c
src/pylzma/pylzma_compressfile.h
src/pylzma/pylzma_compressobj.c
src/pylzma/pylzma_compressobj.h
src/pylzma/pylzma_decompress.c
src/pylzma/pylzma_decompress.h
src/pylzma/pylzma_decompress_compat.c
src/pylzma/pylzma_decompress_compat.h
src/pylzma/pylzma_decompressobj.c
src/pylzma/pylzma_decompressobj.h
src/pylzma/pylzma_decompressobj_compat.c
src/pylzma/pylzma_decompressobj_compat.h
src/pylzma/pylzma_streams.c
src/pylzma/pylzma_streams.h
src/sdk/7zFormat.txt
src/sdk/7zVersion.h
src/sdk/LzFind.c
src/sdk/LzFind.h
src/sdk/LzFindMt.c
src/sdk/LzFindMt.h
src/sdk/LzHash.h
src/sdk/LzmaDec.c
src/sdk/LzmaDec.h
src/sdk/LzmaEnc.c
src/sdk/LzmaEnc.h
src/sdk/Methods.txt
src/sdk/Threads.c
src/sdk/Threads.h
src/sdk/Types.h
src/sdk/history.txt
src/sdk/lzma.txt