Metadata-Version: 1.1
Name: pylzma
Version: 0.4.5
Summary: Python bindings for the LZMA library by Igor Pavlov.
Home-page: http://www.joachim-bauch.de/projects/pylzma/
Author: Joachim Bauch
Author-email: mail@joachim-bauch.de
License: LGPL
Download-URL: http://pypi.python.org/pypi/pylzma/
Keywords: lzma compression
Platform: UNKNOWN
Classifier: Development Status :: 5 - Production/Stable
Classifier: Programming Language :: Python
Classifier: Programming Language :: Python :: 3
Classifier: Topic :: Software Development :: Libraries :: Python Modules
Classifier: Intended Audience :: Developers
Classifier: License :: OSI Approved :: GNU Library or Lesser General Public License (LGPL)
Classifier: Operating System :: OS Independent
